{
"CUSTDISTIdx0" : { "ArrayLength" : "21",  "OptArrayLength" : "19",   "PoolSize" : "0",   "NumElements" : "13",   "NumInArray" : "13"},
"CUSTDIST_mCUSTOMER_IVC1_E1_1Idx0" : { "ArrayLength" : "12983",  "OptArrayLength" : "12983",   "PoolSize" : "0",   "NumElements" : "9179",   "NumInArray" : "8623"},
"CUSTDIST_mCUSTOMER1_L1_1Idx0" : { "ArrayLength" : "21001",  "OptArrayLength" : "21001",   "PoolSize" : "0",   "NumElements" : "15000",   "NumInArray" : "15000"},
"CUSTDIST_mCUSTOMER1_L1_2Idx0" : { "ArrayLength" : "12983",  "OptArrayLength" : "12983",   "PoolSize" : "0",   "NumElements" : "9179",   "NumInArray" : "8623"},
"TmpStore2Idx0" : { "ArrayLength" : "21",  "OptArrayLength" : "19",   "PoolSize" : "0",   "NumElements" : "13",   "NumInArray" : "13"},
"TmpStore4Idx0" : { "ArrayLength" : "1",  "OptArrayLength" : "1",   "PoolSize" : "0",   "NumElements" : "0",   "NumInArray" : "0"},
"TmpStore1Idx0" : { "ArrayLength" : "21",  "OptArrayLength" : "19",   "PoolSize" : "0",   "NumElements" : "13",   "NumInArray" : "13"},
"TmpStore3Idx0" : { "ArrayLength" : "12",  "OptArrayLength" : "12",   "PoolSize" : "0",   "NumElements" : "8",   "NumInArray" : "8"}
}
